psycospans/__init__.py
psycospans/_utils.py
PsycoSpans-1.0.0.dist-info/LICENSE
PsycoSpans-1.0.0.dist-info/METADATA
PsycoSpans-1.0.0.dist-info/WHEEL
PsycoSpans-1.0.0.dist-info/top_level.txt
PsycoSpans-1.0.0.dist-info/RECORD
