Metadata-Version: 2.1
Name: PsycoSpans
Version: 1.0.0
Summary: Psycopg2 support for the Spans library
Home-page: https://www.github.com/runfalk/psycospans
Author: Andreas Runfalk
Author-email: andreas@runfalk.se
License: MIT
Platform: UNKNOWN
Classifier: Development Status :: 5 - Production/Stable
Classifier: Intended Audience :: Developers
Classifier: License :: OSI Approved :: MIT License
Classifier: Programming Language :: Python
Classifier: Programming Language :: Python :: 2.7
Classifier: Programming Language :: Python :: 3.4
Classifier: Programming Language :: Python :: 3.5
Classifier: Programming Language :: Python :: 3.6
Classifier: Programming Language :: Python :: 3.7
Classifier: Topic :: Database
Classifier: Topic :: Utilities
Requires-Dist: spans
Provides-Extra: dev
Requires-Dist: psycopg2-binary; extra == 'dev'
Requires-Dist: pytest; extra == 'dev'
